Metadata-Version: 1.0
Name: pyseqlib
Version: 0.3.1
Summary: pySeqLib: A small python library to process sequencing data.
Home-page: https://github.com/huangyh09/pyseqlib
Author: Yuanhua Huang
Author-email: yuanhua@ebi.ac.uk
License: Apache-2.0
Keywords: sequencing data processing
Platform: UNKNOWN
